{
    "org": {
        "seed": "replace this with an IRUT",
        "name": "Replace w/your org name",
        "location": "Repalce w/your org location",
        "url": "https://mysite.com",
        "email": "admin@mysite.com"
    },
    "site": {
        "seed": "replace this an an IRUT",
        "url": "https://mysite.com",
        "title": "Site Title",
        "description": "A description of your website.",
        "copyright": "Copyright (C) 2016 Replace w/your org name",
        "context": {}
    },
    "generator": {
        "build": {
            "time": 1456125090677,
            "date": "Sun Feb 21 2016 23:11:30 GMT-0800 (PST)",
            "hash": "Sh5MP100T96tzoq6vIibEQ"
        },
        "agent": {
            "name": "snapsite",
            "version": "0.0.5"
        }
    },
    "pagesGraph": {
        "name": "ReactJS UX Route Graph",
        "description": "A directed graph model of undefined routes mapped to ReactJS UX.",
        "vlist": [
            {
                "u": "a90e9ae0",
                "p": {
                    "primaryRouteHash": "a90e9ae0",
                    "primaryRoute": "/",
                    "title": "Route Title",
                    "description": "A route is associated with a ReactJS page by default.",
                    "tooltip": "Some tooltip...",
                    "rank": 0
                }
            },
            {
                "u": "fd1f8812",
                "p": {
                    "primaryRouteHash": "fd1f8812",
                    "primaryRoute": "/installation",
                    "title": "Test Route",
                    "description": "A quick test route.",
                    "tooltip": "Jump to the test route...",
                    "rank": 0
                }
            },
            {
                "u": "f41811ee",
                "p": {
                    "primaryRouteHash": "f41811ee",
                    "primaryRoute": "/testsite",
                    "title": "Home",
                    "description": "Encapsule.io software development website.",
                    "tooltip": "Jump back to the top of the site...",
                    "rank": 9
                }
            },
            {
                "u": "202c309f",
                "p": {
                    "primaryRouteHash": "202c309f",
                    "primaryRoute": "/testsite/about",
                    "title": "About",
                    "description": "Learn about Encapsule.io.",
                    "tooltip": "About Encapsule.io...",
                    "rank": 0
                }
            },
            {
                "u": "1e21dd27",
                "p": {
                    "primaryRouteHash": "1e21dd27",
                    "primaryRoute": "/testsite/blog",
                    "title": "Blog",
                    "description": "Encapsule.io web development blog.",
                    "tooltip": "Encapsule.io blog...",
                    "rank": 0
                }
            },
            {
                "u": "421567c4",
                "p": {
                    "primaryRouteHash": "421567c4",
                    "primaryRoute": "/testsite/colter",
                    "title": "Hello, Colter",
                    "description": "This is a test. Hello!",
                    "tooltip": "Jump to Hello, Colter...",
                    "rank": 0
                }
            },
            {
                "u": "d66b4755",
                "p": {
                    "primaryRouteHash": "d66b4755",
                    "primaryRoute": "/testsite/docs",
                    "title": "Documentation",
                    "description": "Encapsule tools, and libaries documentation library.",
                    "tooltip": "Browse technical documentation...",
                    "rank": 0
                }
            },
            {
                "u": "f840cd18",
                "p": {
                    "primaryRouteHash": "f840cd18",
                    "primaryRoute": "/testsite/new-page",
                    "title": "Hello, John",
                    "description": "A test page to demonstrate some basic capabilities.",
                    "tooltip": "Jump to the Hello, John demo page...",
                    "rank": 0
                }
            },
            {
                "u": "de94d6a8",
                "p": {
                    "primaryRouteHash": "de94d6a8",
                    "primaryRoute": "/testsite/tiffany",
                    "title": "Hello, Tiffany",
                    "description": "This is a simple demo page.",
                    "tooltip": "Jump to Tiff's demo page...",
                    "rank": 0
                }
            },
            {
                "u": "c27356c0",
                "p": {
                    "primaryRouteHash": "c27356c0",
                    "primaryRoute": "/testsite/about/contact",
                    "title": "Contact",
                    "description": "Contact information and directions to Encapsule.io.",
                    "tooltip": "Contact information...",
                    "rank": 0
                }
            }
        ],
        "elist": [
            {
                "e": {
                    "u": "a90e9ae0",
                    "v": "fd1f8812"
                }
            },
            {
                "e": {
                    "u": "a90e9ae0",
                    "v": "f41811ee"
                }
            },
            {
                "e": {
                    "u": "f41811ee",
                    "v": "202c309f"
                }
            },
            {
                "e": {
                    "u": "f41811ee",
                    "v": "1e21dd27"
                }
            },
            {
                "e": {
                    "u": "f41811ee",
                    "v": "421567c4"
                }
            },
            {
                "e": {
                    "u": "f41811ee",
                    "v": "d66b4755"
                }
            },
            {
                "e": {
                    "u": "f41811ee",
                    "v": "f840cd18"
                }
            },
            {
                "e": {
                    "u": "f41811ee",
                    "v": "de94d6a8"
                }
            },
            {
                "e": {
                    "u": "202c309f",
                    "v": "c27356c0"
                }
            }
        ]
    },
    "page": {
        "primaryRouteHash": "1e21dd27",
        "primaryRoute": "/testsite/blog",
        "title": "Blog",
        "description": "Encapsule.io web development blog.",
        "tooltip": "Encapsule.io blog...",
        "rank": 0,
        "context": {}
    },
    "lookup": {
        "routeHashToRouteMap": {
            "a90e9ae0": "/",
            "fd1f8812": "/installation",
            "f41811ee": "/testsite",
            "202c309f": "/testsite/about",
            "1e21dd27": "/testsite/blog",
            "421567c4": "/testsite/colter",
            "d66b4755": "/testsite/docs",
            "f840cd18": "/testsite/new-page",
            "1189e049": "/testsite/static",
            "de94d6a8": "/testsite/tiffany",
            "c27356c0": "/testsite/about/contact"
        },
        "routeToRouteHashMap": {
            "/": "a90e9ae0",
            "/installation": "fd1f8812",
            "/testsite": "f41811ee",
            "/testsite/about": "202c309f",
            "/testsite/blog": "1e21dd27",
            "/testsite/colter": "421567c4",
            "/testsite/docs": "d66b4755",
            "/testsite/new-page": "f840cd18",
            "/testsite/static": "1189e049",
            "/testsite/tiffany": "de94d6a8",
            "/testsite/about/contact": "c27356c0"
        }
    }
}